Metadata-Version: 1.0
Name: automated-competitive-programming
Version: 0.1.2
Summary: Easier competitive programming.
Home-page: UNKNOWN
Author: Dan Sclearov
Author-email: dansclearov@gmail.com
License: UNKNOWN
Platform: UNKNOWN
